{
  "wallpapers": [
    {
      "author": "Nick Nice" ,
      "url": "https://raw.githubusercontent.com/AndroTrix/Wallpapers/master/AndroTrix%201.jpg",
      "name": "Mountains",
      "thumbnail": "https://raw.githubusercontent.com/AndroTrix/Wallpapers/master/AndroTrix%201.jpg"
    },
    {
      "author": "Unknown" ,
      "url": "https://raw.githubusercontent.com/AndroTrix/Wallpapers/master/AndroTrix%2010.jpg",
      "name": "Skeleton",
      "thumbnail": "https://raw.githubusercontent.com/AndroTrix/Wallpapers/master/AndroTrix%2010.jpg"
    },
    {
      "author": "Nick Nice",
      "url": "https://raw.githubusercontent.com/AndroTrix/Wallpapers/master/AndroTrix%2011.jpg",
      "name":" Sunset_1",
      "thumbnail": "https://raw.githubusercontent.com/AndroTrix/Wallpapers/master/AndroTrix%2011.jpg"
    },
    {
      "author": "Nick Nice" ,
      "url": "https://raw.githubusercontent.com/AndroTrix/Wallpapers/master/AndroTrix%2012.jpg",
      "name": "Abstract_1",
      "thumbnail": "https://raw.githubusercontent.com/AndroTrix/Wallpapers/master/AndroTrix%2012.jpg"
    },
    {
      "author": "Nick Nice" ,
      "url": "https://raw.githubusercontent.com/AndroTrix/Wallpapers/master/AndroTrix%2013.png",
      "name": "Jungle",
      "thumbnail": "https://raw.githubusercontent.com/AndroTrix/Wallpapers/master/AndroTrix%2013.png"
    },
    {
      "author": "Nick Nice" ,
      "url": "https://raw.githubusercontent.com/AndroTrix/Wallpapers/master/AndroTrix%2014.jpg",
      "name": "Abstract_2",
      "thumbnail": "https://raw.githubusercontent.com/AndroTrix/Wallpapers/master/AndroTrix%2014.jpg"
    },
    {
      "author": "Nick Nice" ,
      "url": "https://raw.githubusercontent.com/AndroTrix/Wallpapers/master/AndroTrix%2015.jpg",
      "name": "Iron Man",
      "thumbnail": "https://raw.githubusercontent.com/AndroTrix/Wallpapers/master/AndroTrix%2015.jpg"
    },
    {
      "author": "Nick Nice" ,
      "url": "https://raw.githubusercontent.com/AndroTrix/Wallpapers/master/AndroTrix%2016.jpg",
      "name": "Mafia City",
      "thumbnail": "https://raw.githubusercontent.com/AndroTrix/Wallpapers/master/AndroTrix%2016.jpg"
    },
    {
      "author": "Nick Nice" ,
      "url": "https://raw.githubusercontent.com/AndroTrix/Wallpapers/master/AndroTrix%2017.jpg",
      "name": "Earth View_1",
      "thumbnail": "https://raw.githubusercontent.com/AndroTrix/Wallpapers/master/AndroTrix%2017.jpg"
    },
    {
      "author": "Nick Nice" ,
      "url": "https://raw.githubusercontent.com/AndroTrix/Wallpapers/master/AndroTrix%2018.jpg",
      "name": "Earth View_2",
      "thumbnail": "https://raw.githubusercontent.com/AndroTrix/Wallpapers/master/AndroTrix%2018.jpg"
    },
    {
      "author": "Nick Nice" ,
      "url": "https://raw.githubusercontent.com/AndroTrix/Wallpapers/master/AndroTrix%2019.jpg",
      "name": "Sunset_2",
      "thumbnail": "https://raw.githubusercontent.com/AndroTrix/Wallpapers/master/AndroTrix%2019.jpg"
    },
    {
      "author": "Nick Nice" ,
      "url": "https://raw.githubusercontent.com/AndroTrix/Wallpapers/master/AndroTrix%202.png",
      "name": "Earth View_3",
      "thumbnail": "https://raw.githubusercontent.com/AndroTrix/Wallpapers/master/AndroTrix%202.png"
    },
    {
      "author": "Nick Nice" ,
      "url": "https://raw.githubusercontent.com/AndroTrix/Wallpapers/master/AndroTrix%2020.jpg",
      "name": "Abstract_3",
      "thumbnail": "https://raw.githubusercontent.com/AndroTrix/Wallpapers/master/AndroTrix%2020.jpg"
    },
    {
      "author": "Nick Nice" ,
      "url": "https://raw.githubusercontent.com/AndroTrix/Wallpapers/master/AndroTrix%2021.jpg",
      "name": "Flower Boat",
      "thumbnail": "https://raw.githubusercontent.com/AndroTrix/Wallpapers/master/AndroTrix%2021.jpg"
    },
    {
      "author": "Nick Nice" ,
      "url": "https://raw.githubusercontent.com/AndroTrix/Wallpapers/master/AndroTrix%2022.png",
      "name": "Grey City",
      "thumbnail": "https://raw.githubusercontent.com/AndroTrix/Wallpapers/master/AndroTrix%2022.png"
    },
    {
      "author": "Nick Nice" ,
      "url": "https://raw.githubusercontent.com/AndroTrix/Wallpapers/master/AndroTrix%2023.png",
      "name": "Car",
      "thumbnail": "https://raw.githubusercontent.com/AndroTrix/Wallpapers/master/AndroTrix%2023.png"
    },
    {
      "author": "Nick Nice" ,
      "url": "https://raw.githubusercontent.com/AndroTrix/Wallpapers/master/AndroTrix%2024.jpg",
      "name": "NightTime",
      "thumbnail": "https://raw.githubusercontent.com/AndroTrix/Wallpapers/master/AndroTrix%2024.jpg"
    },
    {
      "author": "Nick Nice" ,
      "url": "https://raw.githubusercontent.com/AndroTrix/Wallpapers/master/AndroTrix%203.png",
      "name": "Radium",
      "thumbnail": "https://raw.githubusercontent.com/AndroTrix/Wallpapers/master/AndroTrix%203.png"
    },
    {
      "author": "Nick Nice" ,
      "url": "https://raw.githubusercontent.com/AndroTrix/Wallpapers/master/AndroTrix%204.jpg",
      "name": "Abstract_4",
      "thumbnail": "https://raw.githubusercontent.com/AndroTrix/Wallpapers/master/AndroTrix%204.jpg"
    },
    {
      "author": "Nick Nice" ,
      "url": "https://raw.githubusercontent.com/AndroTrix/Wallpapers/master/AndroTrix%205.jpg",
      "name": "Earth View_4",
      "thumbnail": "https://raw.githubusercontent.com/AndroTrix/Wallpapers/master/AndroTrix%205.jpg"
    },
    {
      "author": "Nick Nice" ,
      "url": "https://raw.githubusercontent.com/AndroTrix/Wallpapers/master/AndroTrix%206.jpg",
      "name": "Earth View_5",
      "thumbnail": "https://raw.githubusercontent.com/AndroTrix/Wallpapers/master/AndroTrix%206.jpg"
    },
    {
      "author": "Nick Nice" ,
      "url": "https://raw.githubusercontent.com/AndroTrix/Wallpapers/master/AndroTrix%207.jpg",
      "name": "Earth View_6",
      "thumbnail": "https://raw.githubusercontent.com/AndroTrix/Wallpapers/master/AndroTrix%201.jpg"
    },
    {
      "author": "Nick Nice" ,
      "url": "https://raw.githubusercontent.com/AndroTrix/Wallpapers/master/AndroTrix%208.jpg",
      "name": "Earth View_7",
      "thumbnail": "https://raw.githubusercontent.com/AndroTrix/Wallpapers/master/AndroTrix%208.jpg"
    },
    {
      "author": "Nick Nice" ,
      "url": "https://raw.githubusercontent.com/AndroTrix/Wallpapers/master/AndroTrix%209.jpg",
      "name": "Earth View_8",
      "thumbnail": "https://raw.githubusercontent.com/AndroTrix/Wallpapers/master/AndroTrix%209.jpg"
    }
  ]
}